Find-Python.ps1
LICENSE.txt
MANIFEST.in
Test-Pyvot.ps1
setup.cfg
setup.py
setup.py2.cfg
setup.py3.cfg
Pyvot.egg-info/PKG-INFO
Pyvot.egg-info/SOURCES.txt
Pyvot.egg-info/dependency_links.txt
Pyvot.egg-info/top_level.txt
Pyvot.egg-info/zip-safe
doc/src/conf.py
doc/src/index.rst
doc/src/intro.rst
doc/src/tutorial.rst
doc/src/workflows.rst
doc/src/api/api_index.rst
doc/src/api/cache.rst
doc/src/api/default.rst
doc/src/api/range.rst
doc/src/api/sheet.rst
doc/src/api/tools.rst
doc/src/images/alaska.png
doc/src/images/alaska_filtered.png
doc/src/images/alaska_join_city.png
doc/src/images/alaska_join_final.png
doc/src/images/alaska_join_pop.png
doc/src/images/alaska_map.png
doc/src/images/autofilter.png
doc/src/images/hidden_column.png
doc/src/images/named_range.png
doc/src/images/shell.png
doc/src/images/view.png
doc/src/images/view_post_delete.png
test/TestBook.xlsx
test/TestJoin.xlsx
test/TestPerf.xlsx
test/TestXl.py
xl/__init__.py
xl/cache.py
xl/range.py
xl/sheet.py
xl/shell.py
xl/tools.py
xl/version.py
xl/_impl/__init__.py
xl/_impl/collapsed_matrix.py
xl/_impl/com_utils.py
xl/_impl/table.py