Metadata-Version: 1.0
Name: Pyvot
Version: 0.1.2
Summary: Pythonic interface for data exploration in Excel
Home-page: http://pytools.codeplex.com/wikipage?title=Pyvot
Author: Microsoft Corporation
Author-email: vspython@microsoft.com
License: Apache License 2.0
Download-URL: http://pypi.python.org/pypi/Pyvot
Platform: UNKNOWN
Classifier: Development Status :: 4 - Beta
Classifier: Environment :: Win32 (MS Windows)
Classifier: Operating System :: Microsoft :: Windows
Classifier: Programming Language :: Python
Classifier: Programming Language :: Python :: 2
Classifier: Programming Language :: Python :: 3
Classifier: Topic :: Office/Business :: Financial :: Spreadsheet
Classifier: License :: OSI Approved :: Apache Software License
